<?xml version="1.0" encoding="UTF-8" standalone="yes"?>
<hierarchy rotation="0">
	<node index="0" text="" resource-id="" class="android.widget.FrameLayout" package="com.whatsapp" content-desc="" checkable="false" checked="false" clickable="false" enabled="true" focusable="false" focused="false" scrollable="false" long-clickable="false" password="false" selected="false" bounds="[0,0][1080,2160]">
		<node index="0" text="" resource-id="" class="android.widget.LinearLayout" package="com.whatsapp" content-desc="" checkable="false" checked="false" clickable="false" enabled="true" focusable="false" focused="false" scrollable="false" long-clickable="false" password="false" selected="false" bounds="[0,0][1080,2160]">
			<node index="0" text="" resource-id="" class="android.widget.FrameLayout" package="com.whatsapp" content-desc="" checkable="false" checked="false" clickable="false" enabled="true" focusable="false" focused="false" scrollable="false" long-clickable="false" password="false" selected="false" bounds="[0,113][1080,2160]">
				<node index="0" text="" resource-id="com.whatsapp:id/decor_content_parent" class="android.view.ViewGroup" package="com.whatsapp" content-desc="" checkable="false" checked="false" clickable="false" enabled="true" focusable="false" focused="false" scrollable="false" long-clickable="false" password="false" selected="false" bounds="[0,113][1080,2160]">
					<node index="0" text="" resource-id="com.whatsapp:id/action_bar_container" class="android.widget.FrameLayout" package="com.whatsapp" content-desc="" checkable="false" checked="false" clickable="false" enabled="true" focusable="false" focused="false" scrollable="false" long-clickable="false" password="false" selected="false" bounds="[0,113][1080,271]">
						<node index="0" text="" resource-id="com.whatsapp:id/action_bar" class="android.view.ViewGroup" package="com.whatsapp" content-desc="" checkable="false" checked="false" clickable="false" enabled="true" focusable="false" focused="false" scrollable="false" long-clickable="false" password="false" selected="false" bounds="[0,113][1080,271]">
							<node index="0" text="" resource-id="" class="android.widget.ImageButton" package="com.whatsapp" content-desc="Navigate up" checkable="false" checked="false" clickable="true" enabled="true" focusable="true" focused="false" scrollable="false" long-clickable="false" password="false" selected="false" bounds="[0,113][158,271]" />
							<node index="1" text="Profile" resource-id="" class="android.widget.TextView" package="com.whatsapp" content-desc="" checkable="false" checked="false" clickable="false" enabled="true" focusable="false" focused="false" scrollable="false" long-clickable="false" password="false" selected="false" bounds="[202,154][367,230]" />
						</node>
					</node>
					<node index="1" text="" resource-id="android:id/content" class="android.widget.FrameLayout" package="com.whatsapp" content-desc="" checkable="false" checked="false" clickable="false" enabled="true" focusable="false" focused="false" scrollable="false" long-clickable="false" password="false" selected="false" bounds="[0,271][1080,2160]">
						<node index="0" text="" resource-id="" class="android.widget.ScrollView" package="com.whatsapp" content-desc="" checkable="false" checked="false" clickable="false" enabled="true" focusable="true" focused="false" scrollable="false" long-clickable="false" password="false" selected="false" bounds="[0,271][1080,2160]">
							<node index="0" text="" resource-id="" class="android.widget.LinearLayout" package="com.whatsapp" content-desc="" checkable="false" checked="false" clickable="false" enabled="true" focusable="false" focused="false" scrollable="false" long-clickable="false" password="false" selected="false" bounds="[0,271][1080,1571]">
								<node index="0" text="" resource-id="" class="android.widget.RelativeLayout" package="com.whatsapp" content-desc="" checkable="false" checked="false" clickable="false" enabled="true" focusable="false" focused="false" scrollable="false" long-clickable="false" password="false" selected="false" bounds="[0,271][1080,840]">
									<node index="0" text="" resource-id="" class="android.widget.FrameLayout" package="com.whatsapp" content-desc="" checkable="false" checked="false" clickable="false" enabled="true" focusable="false" focused="false" scrollable="false" long-clickable="false" password="false" selected="false" bounds="[314,271][766,840]">
										<node index="0" text="" resource-id="com.whatsapp:id/photo_btn" class="android.widget.ImageView" package="com.whatsapp" content-desc="Profile photo" checkable="false" checked="false" clickable="true" enabled="true" focusable="true" focused="false" scrollable="false" long-clickable="false" password="false" selected="false" bounds="[315,339][765,789]" />
										<node index="1" text="" resource-id="com.whatsapp:id/change_photo_btn" class="android.widget.ImageButton" package="com.whatsapp" content-desc="Edit photo" checkable="false" checked="false" clickable="true" enabled="true" focusable="true" focused="false" scrollable="false" long-clickable="false" password="false" selected="false" bounds="[630,654][765,789]" />
									</node>
								</node>
								<node index="1" text="" resource-id="com.whatsapp:id/profile_info_name_card" class="android.widget.LinearLayout" package="com.whatsapp" content-desc="" checkable="false" checked="false" clickable="true" enabled="true" focusable="true" focused="false" scrollable="false" long-clickable="false" password="false" selected="false" bounds="[0,840][1080,1161]">
									<node index="0" text="" resource-id="" class="android.widget.LinearLayout" package="com.whatsapp" content-desc="" checkable="false" checked="false" clickable="false" enabled="true" focusable="false" focused="false" scrollable="false" long-clickable="false" password="false" selected="false" bounds="[0,885][1080,999]">
										<node index="0" text="" resource-id="com.whatsapp:id/profile_settings_row_icon" class="android.widget.ImageView" package="com.whatsapp" content-desc="" checkable="false" checked="false" clickable="false" enabled="true" focusable="false" focused="false" scrollable="false" long-clickable="false" password="false" selected="false" bounds="[68,908][136,976]" />
										<node index="1" text="" resource-id="" class="android.widget.LinearLayout" package="com.whatsapp" content-desc="" checkable="false" checked="false" clickable="false" enabled="true" focusable="false" focused="false" scrollable="false" long-clickable="false" password="false" selected="false" bounds="[204,885][944,999]">
											<node index="0" text="Name" resource-id="com.whatsapp:id/profile_settings_row_text" class="android.widget.TextView" package="com.whatsapp" content-desc="" checkable="false" checked="false" clickable="false" enabled="true" focusable="false" focused="false" scrollable="false" long-clickable="false" password="false" selected="false" bounds="[204,885][308,938]" />
											<node index="1" text="joniyyy" resource-id="com.whatsapp:id/profile_settings_row_subtext" class="android.widget.TextView" package="com.whatsapp" content-desc="" checkable="false" checked="false" clickable="false" enabled="true" focusable="false" focused="false" scrollable="false" long-clickable="false" password="false" selected="false" bounds="[204,938][340,999]" />
										</node>
										<node index="2" text="" resource-id="com.whatsapp:id/profile_settings_row_secondary_icon" class="android.widget.ImageView" package="com.whatsapp" content-desc="" checkable="false" checked="false" clickable="false" enabled="true" focusable="false" focused="false" scrollable="false" long-clickable="false" password="false" selected="false" bounds="[944,908][1012,976]" />
									</node>
									<node index="1" text="" resource-id="" class="android.widget.LinearLayout" package="com.whatsapp" content-desc="" checkable="false" checked="false" clickable="false" enabled="true" focusable="false" focused="false" scrollable="false" long-clickable="false" password="false" selected="false" bounds="[0,999][1080,1116]">
										<node index="0" text="This is not your username or pin. This name will be visible to your WhatsApp contacts." resource-id="com.whatsapp:id/profile_settings_row_description" class="android.widget.TextView" package="com.whatsapp" content-desc="" checkable="false" checked="false" clickable="false" enabled="true" focusable="false" focused="false" scrollable="false" long-clickable="false" password="false" selected="false" bounds="[204,1022][1012,1116]" />
									</node>
								</node>
								<node index="2" text="" resource-id="" class="android.view.View" package="com.whatsapp" content-desc="" checkable="false" checked="false" clickable="false" enabled="true" focusable="false" focused="false" scrollable="false" long-clickable="false" password="false" selected="false" bounds="[203,1161][1080,1162]" />
								<node index="3" text="" resource-id="com.whatsapp:id/profile_info_status_card" class="android.widget.LinearLayout" package="com.whatsapp" content-desc="" checkable="false" checked="false" clickable="true" enabled="true" focusable="true" focused="false" scrollable="false" long-clickable="false" password="false" selected="false" bounds="[0,1162][1080,1366]">
									<node index="0" text="" resource-id="" class="android.widget.LinearLayout" package="com.whatsapp" content-desc="" checkable="false" checked="false" clickable="false" enabled="true" focusable="false" focused="false" scrollable="false" long-clickable="false" password="false" selected="false" bounds="[0,1207][1080,1321]">
										<node index="0" text="" resource-id="com.whatsapp:id/profile_settings_row_icon" class="android.widget.ImageView" package="com.whatsapp" content-desc="" checkable="false" checked="false" clickable="false" enabled="true" focusable="false" focused="false" scrollable="false" long-clickable="false" password="false" selected="false" bounds="[68,1230][136,1298]" />
										<node index="1" text="" resource-id="" class="android.widget.LinearLayout" package="com.whatsapp" content-desc="" checkable="false" checked="false" clickable="false" enabled="true" focusable="false" focused="false" scrollable="false" long-clickable="false" password="false" selected="false" bounds="[204,1207][944,1321]">
											<node index="0" text="About" resource-id="com.whatsapp:id/profile_settings_row_text" class="android.widget.TextView" package="com.whatsapp" content-desc="" checkable="false" checked="false" clickable="false" enabled="true" focusable="false" focused="false" scrollable="false" long-clickable="false" password="false" selected="false" bounds="[204,1207][308,1260]" />
											<node index="1" text="Hey there! I am using WhatsApp." resource-id="com.whatsapp:id/profile_settings_row_subtext" class="android.widget.TextView" package="com.whatsapp" content-desc="" checkable="false" checked="false" clickable="false" enabled="true" focusable="false" focused="false" scrollable="false" long-clickable="false" password="false" selected="false" bounds="[204,1260][853,1321]" />
										</node>
										<node index="2" text="" resource-id="com.whatsapp:id/profile_settings_row_secondary_icon" class="android.widget.ImageView" package="com.whatsapp" content-desc="" checkable="false" checked="false" clickable="false" enabled="true" focusable="false" focused="false" scrollable="false" long-clickable="false" password="false" selected="false" bounds="[944,1230][1012,1298]" />
									</node>
								</node>
								<node index="4" text="" resource-id="" class="android.view.View" package="com.whatsapp" content-desc="" checkable="false" checked="false" clickable="false" enabled="true" focusable="false" focused="false" scrollable="false" long-clickable="false" password="false" selected="false" bounds="[203,1366][1080,1367]" />
								<node index="5" text="" resource-id="com.whatsapp:id/profile_phone_info" class="android.widget.LinearLayout" package="com.whatsapp" content-desc="" checkable="false" checked="false" clickable="true" enabled="true" focusable="true" focused="false" scrollable="false" long-clickable="false" password="false" selected="false" bounds="[0,1367][1080,1571]">
									<node index="0" text="" resource-id="" class="android.widget.LinearLayout" package="com.whatsapp" content-desc="" checkable="false" checked="false" clickable="false" enabled="true" focusable="false" focused="false" scrollable="false" long-clickable="false" password="false" selected="false" bounds="[0,1412][1080,1526]">
										<node index="0" text="" resource-id="com.whatsapp:id/profile_settings_row_icon" class="android.widget.ImageView" package="com.whatsapp" content-desc="" checkable="false" checked="false" clickable="false" enabled="true" focusable="false" focused="false" scrollable="false" long-clickable="false" password="false" selected="false" bounds="[68,1435][136,1503]" />
										<node index="1" text="" resource-id="" class="android.widget.LinearLayout" package="com.whatsapp" content-desc="" checkable="false" checked="false" clickable="false" enabled="true" focusable="false" focused="false" scrollable="false" long-clickable="false" password="false" selected="false" bounds="[204,1412][1080,1526]">
											<node index="0" text="Phone" resource-id="com.whatsapp:id/profile_settings_row_text" class="android.widget.TextView" package="com.whatsapp" content-desc="" checkable="false" checked="false" clickable="false" enabled="true" focusable="false" focused="false" scrollable="false" long-clickable="false" password="false" selected="false" bounds="[204,1412][315,1465]" />
											<node index="1" text="+62 856-4131-2343" resource-id="com.whatsapp:id/profile_settings_row_subtext" class="android.widget.TextView" package="com.whatsapp" content-desc="" checkable="false" checked="false" clickable="false" enabled="true" focusable="false" focused="false" scrollable="false" long-clickable="false" password="false" selected="false" bounds="[204,1465][590,1526]" />
										</node>
									</node>
								</node>
							</node>
						</node>
					</node>
				</node>
			</node>
		</node>
		<node index="1" text="" resource-id="android:id/statusBarBackground" class="android.view.View" package="com.whatsapp" content-desc="" checkable="false" checked="false" clickable="false" enabled="true" focusable="false" focused="false" scrollable="false" long-clickable="false" password="false" selected="false" bounds="[0,0][1080,113]" />
		<node index="2" text="" resource-id="android:id/navigationBarBackground" class="android.view.View" package="com.whatsapp" content-desc="" checkable="false" checked="false" clickable="false" enabled="true" focusable="false" focused="false" scrollable="false" long-clickable="false" password="false" selected="false" bounds="[0,0][0,0]" />
	</node>
</hierarchy>
